hwp_convert_code/__init__.py
hwp_convert_code/excute/__init__.py
hwp_convert_code/excute/error_manage/__init__.py
hwp_convert_code/excute/error_manage/data_cleansing_error.py
hwp_convert_code/excute/error_manage/data_parsing_error.py
hwp_convert_code/excute/error_manage/hwp_convert_error.py
hwp_convert_code/excute/file_converting/__init__.py
hwp_convert_code/excute/file_converting/config.py
hwp_convert_code/excute/file_converting/file_converting.py
hwp_convert_code/excute/file_converting/hwp_to_html_convert.py
hwp_convert_code/excute/file_converting/hwp_to_pdf_convert.py
hwp_convert_code/excute/file_converting/mlt_prcs.py
hwp_convert_code/excute/file_converting/mlt_prcs_other.py
hwp_convert_code/excute/file_converting/pdf_to_html_convert.py
hthPkg-0.0.41.dist-info/METADATA
hthPkg-0.0.41.dist-info/WHEEL
hthPkg-0.0.41.dist-info/top_level.txt
hthPkg-0.0.41.dist-info/RECORD
