Metadata-Version: 2.1
Name: hthPkg
Version: 0.0.41
Summary: A small example package
Home-page: https://github.com/pypa/sampleproject
Author: Example Author
Author-email: author@example.com
License: UNKNOWN
Platform: UNKNOWN
Classifier: Programming Language :: Python :: 3
Classifier: License :: OSI Approved :: MIT License
Classifier: Operating System :: OS Independent
Requires-Python: >=3.6
Requires-Dist: Django (==3.0.3)
Requires-Dist: configparser (==4.0.2)
Requires-Dist: django-cors-headers (==3.2.1)
Requires-Dist: djangorestframework (==3.11.0)
Requires-Dist: pycryptodome (==3.9.7)
Requires-Dist: mysqlclient (==1.4.6)
Requires-Dist: sqlalchemy (==1.3.13)
Requires-Dist: pdfminer.six (==20191110)
Requires-Dist: requests (==2.22.0)
Requires-Dist: six (==1.13.0)
Requires-Dist: xlrd (==1.2.0)
Requires-Dist: XlsxWriter (==1.2.3)
Requires-Dist: pymysql (==0.9.3)
Requires-Dist: lxml (==4.4.2)
Requires-Dist: pyhwp (==0.1b12)
Requires-Dist: BeautifulSoup4 (==4.8.2)
Requires-Dist: filelock (==3.0.12)
